wikipedia_mcp/__init__.py
wikipedia_mcp/__main__.py
wikipedia_mcp/server.py
wikipedia_mcp/wikipedia_client.py
wikipedia_mcp-1.7.0.dist-info/licenses/LICENSE
wikipedia_mcp-1.7.0.dist-info/METADATA
wikipedia_mcp-1.7.0.dist-info/WHEEL
wikipedia_mcp-1.7.0.dist-info/entry_points.txt
wikipedia_mcp-1.7.0.dist-info/top_level.txt
wikipedia_mcp-1.7.0.dist-info/RECORD
