Metadata-Version: 2.4
Name: wikipedia-mcp
Version: 1.7.0
Summary: MCP server for Wikipedia API
Author-email: Ravi Kumar E <ravikumar@ravikumar-dev.me>
License-Expression: MIT
Project-URL: Homepage, https://github.com/rudra-ravi/wikipedia-mcp
Project-URL: Repository, https://github.com/rudra-ravi/wikipedia-mcp
Project-URL: Issues, https://github.com/rudra-ravi/wikipedia-mcp/issues
Project-URL: Documentation, https://github.com/rudra-ravi/wikipedia-mcp#readme
Keywords: mcp,wikipedia,model-context-protocol,ai,llm
Classifier: Programming Language :: Python :: 3.10
Classifier: Programming Language :: Python :: 3.11
Classifier: Programming Language :: Python :: 3.12
Classifier: Operating System :: OS Independent
Classifier: Development Status :: 4 - Beta
Classifier: Intended Audience :: Developers
Classifier: Topic :: Software Development :: Libraries :: Python Modules
Requires-Python: >=3.10
License-File: LICENSE
Requires-Dist: fastmcp>=2.3.0
Requires-Dist: wikipedia-api>=0.8.0
Requires-Dist: requests>=2.31.0
Requires-Dist: python-dotenv>=1.0.0
Provides-Extra: dev
Requires-Dist: pytest>=7.0.0; extra == "dev"
Requires-Dist: pytest-cov>=4.0.0; extra == "dev"
Requires-Dist: pytest-mock>=3.10.0; extra == "dev"
Requires-Dist: pytest-asyncio>=0.21.0; extra == "dev"
Requires-Dist: black>=23.0.0; extra == "dev"
Requires-Dist: flake8>=6.0.0; extra == "dev"
Requires-Dist: mypy>=1.0.0; extra == "dev"
Dynamic: license-file
